pyloop
app
