Metadata-Version: 1.1
Name: pyloop
Version: 0.12
Summary: An universal pacakge manager for python
Home-page: https://github.com/Hedronium/pyloop
Author: Hedronium
Author-email: project.anik@gmail.com
License: MIT
Download-URL: https://github.com/Hedronium/pyloop/tarball/0.12
Keywords: package manger,python 3
Platform: UNKNOWN
